{
  "page": [{
    "name": "Daftar Situs Tanggap COVID-19",
    "description": "Daftar situs tanggap COVID-19 milik Pemerintah Pusat, Pemerintah Daerah, dan lainnya.",
    "author": "Muhammad Hanif - hanifmu.com",
    "url": "https://corona.hanifmu.com/pranala/"
  }],
  "features": [{
    "attributes": {
      "group_name": "PEMERINTAH PUSAT",
      "slug": "pemerintah-pusat",
      "lists": [{
        "name": "Kementerian Kesehatan",
        "url": "https://infeksiemerging.kemkes.go.id/"
      }, {
        "name": "Gugus Tugas Percepatan Penanganan COVID-19",
        "url": "https://www.covid19.go.id/"
      }, {
        "name": "Peta Rumah Sakit Rujukan COVID-19",
        "url": "https://bnpb-inacovid19.hub.arcgis.com/app/rumah-sakit-rujukan-penanganan-covid-19"
      }, {
        "name": "Data Kasus dan Peta Persebaran COVID-19",
        "url": "https://experience.arcgis.com/experience/57237ebe9c5b4b1caa1b93e79c920338"
      }, {
        "name": "PeduliLindungi",
        "url": "https://www.pedulilindungi.id/"
      }]
    }
  }, {
    "attributes": {
      "group_name": "ACEH",
      "slug": "aceh",
      "lists": [{
        "name": "Pemerintah Provinsi Aceh",
        "url": "https://covid19.acehprov.go.id/"
      }]
    }
  }, {
    "attributes": {
      "group_name": "Bali",
      "slug": "bali",
      "lists": [{
        "name": "Pemerintah Provinsi Bali",
        "url": "https://infocorona.baliprov.go.id/"
      }]
    }
  }, {
    "attributes": {
      "group_name": "BANTEN",
      "slug": "banten",
      "lists": [{
        "name": "Pemerintah Provinsi Banten",
        "url": "https://infocorona.bantenprov.go.id/"
      }, {
        "name": "Pemerintah Kabupaten Lebak",
        "url": "https://siagacovid19.lebakkab.go.id/"
      }, {
        "name": "Pemerintah Kabupaten Pandeglang",
        "url": "https://infocorona.pandeglangkab.go.id/"
      }, {
        "name": "Pemerintah Kabupaten Serang",
        "url": "https://infocorona.serangkab.go.id/"
      }, {
        "name": "Pemerintah Kabupaten Tangerang",
        "url": "http://covid19.tangerangkab.go.id/"
      }, {
        "name": "Pemerintah Kota Cilegon",
        "url": "http://covid19.cilegon.go.id/"
      }, {
        "name": "Pemerintah Kota Serang",
        "url": "https://infocorona.serangkota.go.id/"
      }, {
        "name": "Pemerintah Kota Tangerang",
        "url": "https://maps.tangerangkota.go.id/corona/"
      }]
    }
  }, {
    "attributes": {
      "group_name": "JAKARTA",
      "slug": "jakarta",
      "lists": [{
        "name": "Pemerintah Provinsi DKI Jakarta",
        "url": "https://corona.jakarta.go.id/"
      }]
    }
  }, {
    "attributes": {
      "group_name": "JAMBI",
      "slug": "jambi",
      "lists": [{
        "name": "Pemerintah Kabupaten Bungo",
        "url": "https://covid19.bungokab.go.id/"
      }]
    }
  }, {
    "attributes": {
      "group_name": "JAWA BARAT",
      "slug": "jawa-barat",
      "lists": [{
        "name": "Pemerintah Provinsi Jawa Barat",
        "url": "https://pikobar.jabarprov.go.id/"
      }, {
        "name": "Pemerintah Kabupaten Bandung",
        "url": "https://covid19.bandungkab.go.id/"
      }, {
        "name": "Pemerintah Kabupaten Bandung Barat",
        "url": "https://pik.bandungbaratkab.go.id/"
      }, {
        "name": "Pemerintah Kabupaten Bekasi",
        "url": "https://pikokabsi.bekasikab.go.id/"
      }, {
        "name": "Pemerintah Kabupaten Bogor",
        "url": "https://covid-19.bogorkab.go.id/"
      }, {
        "name": "Pemerintah Kabupaten Cianjur",
        "url": "https://covid19.cianjurkab.go.id/"
      }, {
        "name": "Pemerintah Kabupaten Cirebon",
        "url": "http://covid19.cirebonkab.go.id/"
      }, {
        "name": "Pemerintah Kabupaten Indramayu",
        "url": "https://covid19.indramayukab.go.id/"
      }, {
        "name": "Pemerintah Kabupaten Karawang",
        "url": "http://covid19.karawangkab.go.id/"
      }, {
        "name": "Pemerintah Kabupaten Majalengka",
        "url": "https://covid19.majalengkakab.go.id/"
      }, {
        "name": "Pemerintah Kabupaten Pangandaran",
        "url": "https://covid19.pangandarankab.go.id/"
      }, {
        "name": "Pemerintah Kabupaten Purwakarta",
        "url": "http://covid19.purwakartakab.go.id/"
      }, {
        "name": "Pemerintah Kabupaten Subang",
        "url": "https://covid19.subang.go.id/"
      }, {
        "name": "Pemerintah Kabupaten Sumedang",
        "url": "http://covid19.sumedangkab.go.id/"
      }, {
        "name": "Pemerintah Kabupaten Tasikmalaya",
        "url": "https://tasikmalayakab.go.id/index.php/en/aneka-info/info-covid19"
      }, {
        "name": "Pemerintah Kota Bandung",
        "url": "https://covid19.bandung.go.id/"
      }, {
        "name": "Pemerintah Kota Bekasi",
        "url": "http://corona.bekasikota.go.id/"
      }, {
        "name": "Pemerintah Kota Bogor",
        "url": "http://www.covid19.kotabogor.go.id/"
      }, {
        "name": "Pemerintah Kota Cimahi",
        "url": "https://covid19.cimahikota.go.id/"
      }, {
        "name": "Pemerintah Kota Cirebon",
        "url": "https://covid19.cirebonkota.go.id/"
      }, {
        "name": "Pemerintah Kota Depok",
        "url": "http://ccc-19.depok.go.id/"
      }, {
        "name": "Pemerintah Kota Sukabumi",
        "url": "https://covid19.sukabumikota.go.id/"
      }]
    }
  }, {
    "attributes": {
      "group_name": "JAWA TENGAH",
      "slug": "jawa-tengah",
      "lists": [{
        "name": "Pemerintah Provinsi Jawa Tengah",
        "url": "https://corona.jatengprov.go.id/"
      }, {
        "name": "Pemerintah Kabupaten Banjarnegara",
        "url": "http://corona.banjarnegarakab.go.id/"
      }, {
        "name": "Pemerintah Kabupaten Banyumas",
        "url": "http://covid19.banyumaskab.go.id/"
      }, {
        "name": "Pemerintah Kabupaten Batang",
        "url": "https://corona.batangkab.go.id/"
      }, {
        "name": "Pemerintah Kabupaten Blora",
        "url": "http://corona.blorakab.go.id/"
      }, {
        "name": "Pemerintah Kabupaten Boyolali",
        "url": "http://covid19.boyolali.go.id/"
      }, {
        "name": "Pemerintah Kabupaten Brebes",
        "url": "http://corona.brebeskab.go.id/"
      }, {
        "name": "Pemerintah Kabupaten Cilacap",
        "url": "https://corona.cilacapkab.go.id/"
      }, {
        "name": "Pemerintah Kabupaten Demak",
        "url": "http://corona.demakkab.go.id//"
      }, {
        "name": "Pemerintah Kabupaten Grobogan",
        "url": "https://corona.grobogan.go.id/"
      }, {
        "name": "Pemerintah Kabupaten Jepara",
        "url": "http://corona.jepara.go.id/"
      }, {
        "name": "Pemerintah Kabupaten Karanganyar",
        "url": "http://covid19.karanganyarkab.go.id/"
      }, {
        "name": "Pemerintah Kabupaten Kebumen",
        "url": "https://corona.kebumenkab.go.id/"
      }, {
        "name": "Pemerintah Kabupaten Kendal",
        "url": "https://corona.kendalkab.go.id/"
      }, {
        "name": "Pemerintah Kabupaten Klaten",
        "url": "http://pantaucorona.klatenkab.go.id/"
      }, {
        "name": "Pemerintah Kabupaten Kudus",
        "url": "http://corona.kuduskab.go.id/"
      }, {
        "name": "Pemerintah Kabupaten Magelang",
        "url": "https://infocorona.magelangkab.go.id/"
      }, {
        "name": "Pemerintah Kabupaten Pati",
        "url": "https://covid19.patikab.go.id/"
      }, {
        "name": "Pemerintah Kabupaten Pekalongan",
        "url": "http://corona.pekalongankab.go.id/"
      }, {
        "name": "Pemerintah Kabupaten Pemalang",
        "url": "https://infocorona.pemalangkab.go.id/"
      }, {
        "name": "Pemerintah Kabupaten Purbalingga",
        "url": "https://corona.purbalinggakab.go.id/"
      }, {
        "name": "Pemerintah Kabupaten Purworejo",
        "url": "https://covid19.purworejokab.go.id/"
      }, {
        "name": "Pemerintah Kabupaten Rembang",
        "url": "https://covid19.rembangkab.go.id/"
      }, {
        "name": "Pemerintah Kabupaten Semarang",
        "url": "https://corona.semarangkab.go.id/"
      }, {
        "name": "Pemerintah Kabupaten Sragen",
        "url": "http://corona.sragenkab.go.id/"
      }, {
        "name": "Pemerintah Kabupaten Sukoharjo",
        "url": "https://corona.sukoharjokab.go.id/"
      }, {
        "name": "Pemerintah Kabupaten Tegal",
        "url": "https://covid19.tegalkab.go.id/"
      }, {
        "name": "Pemerintah Kabupaten Temanggung",
        "url": "http://corona.temanggungkab.go.id/"
      }, {
        "name": "Pemerintah Kabupaten Wonogiri",
        "url": "https://wonogirikab.go.id/index.php/info-corona/"
      }, {
        "name": "Pemerintah Kabupaten Wonosobo",
        "url": "https://corona.wonosobokab.go.id/"
      }, {
        "name": "Pemerintah Kota Magelang",
        "url": "https://corona.pekalongankota.go.id/"
      }, {
        "name": "Pemerintah Kota Pekalongan",
        "url": "https://covid19.magelangkota.go.id/"
      }, {
        "name": "Pemerintah Kota Salatiga",
        "url": "https://corona.salatiga.go.id/"
      }, {
        "name": "Pemerintah Kota Semarang",
        "url": "https://siagacorona.semarangkota.go.id/"
      }, {
        "name": "Pemerintah Kota Surakarta",
        "url": "https://surakarta.go.id/?page_id=10806"
      }, {
        "name": "Pemerintah Kota Tegal",
        "url": "https://corona.tegalkota.go.id/"
      }]
    }
  }, {
    "attributes": {
      "group_name": "JAWA TIMUR",
      "slug": "jawa-timur",
      "lists": [{
        "name": "Pemerintah Provinsi Jawa Timur",
        "url": "https://infocovid19.jatimprov.go.id/"
      }, {
        "name": "Pemerintah Kabupaten Bangkalan",
        "url": "http://www.bangkalankab.go.id/v5/"
      }, {
        "name": "Pemerintah Kabupaten Banyuwangi",
        "url": "https://corona.banyuwangikab.go.id/"
      }, {
        "name": "Pemerintah Kabupaten Blitar",
        "url": "https://tanggapcorona.blitarkab.go.id/"
      }, {
        "name": "Pemerintah Kabupaten Gresik",
        "url": "https://satgascovid19.gresikkab.go.id/"
      }, {
        "name": "Pemerintah Kabupaten Jember",
        "url": "http://www.jemberkab.go.id/data-covid-19/"
      }, {
        "name": "Pemerintah Kabupaten Jombang",
        "url": "https://dinkes.jombangkab.go.id/data-covid-19-kabupaten-jombang"
      }, {
        "name": "Pemerintah Kabupaten Kediri",
        "url": "https://covid19.kedirikab.go.id/"
      }, {
        "name": "Pemerintah Kabupaten Lamongan",
        "url": "https://lamongankab.go.id/dinkes/"
      }, {
        "name": "Pemerintah Kabupaten Lumajang",
        "url": "https://infocovid19.lumajangkab.go.id/"
      }, {
        "name": "Pemerintah Kabupaten Madiun",
        "url": "https://madiunkab.go.id/"
      }, {
        "name": "Pemerintah Kabupaten Magetan",
        "url": "http://kominfo.magetan.go.id/id/artikel/"
      }, {
        "name": "Pemerintah Kabupaten Malang",
        "url": "http://satgascovid19.malangkab.go.id/"
      }, {
        "name": "Pemerintah Kabupaten Mojokerto",
        "url": "http://covid19.mojokertokab.go.id/"
      }, {
        "name": "Pemerintah Kabupaten Nganjuk",
        "url": "https://www.nganjukkab.go.id/beranda/CoronaController/pencegahanCorona"
      }, {
        "name": "Pemerintah Kabupaten Pacitan",
        "url": "https://covid19.pacitankab.go.id/"
      }, {
        "name": "Pemerintah Kabupaten Pamekasan",
        "url": "http://covid19.pamekasankab.go.id/"
      }, {
        "name": "Pemerintah Kabupaten Ponorogo",
        "url": "https://ponorogo.go.id/corona/"
      }, {
        "name": "Pemerintah Kabupaten Sampang",
        "url": "https://sampangkab.go.id/covid-19/"
      }, {
        "name": "Pemerintah Kabupaten Sidoarjo",
        "url": "https://covid19.sidoarjokab.go.id/"
      }, {
        "name": "Pemerintah Kabupaten Tuban",
        "url": "https://tubankab.go.id/page/informasi-tentang-virus-corona-covid-19"
      }, {
        "name": "Pemerintah Kabupaten Tulungagung",
        "url": "https://covid19.tulungagung.go.id/"
      }, {
        "name": "Pemerintah Kota Batu",
        "url": "https://covid19.batukota.go.id/"
      }, {
        "name": "Pemerintah Kota Kediri",
        "url": "https://corona.kedirikota.go.id/"
      }, {
        "name": "Pemerintah Kota Madiun",
        "url": "http://covid19.madiunkota.go.id/"
      }, {
        "name": "Pemerintah Kota Malang",
        "url": "http://coronadetektor.malangkota.go.id/"
      }, {
        "name": "Pemerintah Kota Mojokerto",
        "url": "http://covid19.mojokertokota.go.id/"
      }, {
        "name": "Pemerintah Kota Probolinggo",
        "url": "https://portal.probolinggokota.go.id/index.php/tanggap-corona/"
      }, {
        "name": "Pemerintah Kota Surabaya",
        "url": "https://lawancovid-19.surabaya.go.id/"
      }]
    }
  }, {
    "attributes": {
      "group_name": "KALIMANTAN BARAT",
      "slug": "kalimantan-barat",
      "lists": [{
        "name": "Pemerintah Provinsi Kalimantan Barat",
        "url": "https://dinkes.kalbarprov.go.id/covid-19/"
      }]
    }
  }, {
    "attributes": {
      "group_name": "KALIMANTAN SELATAN",
      "slug": "kalimantan-selatan",
      "lists": [{
        "name": "Pemerintah Provinsi Kalimantan Selatan",
        "url": "http://corona.kalselprov.go.id/"
      }]
    }
  }, {
    "attributes": {
      "group_name": "KALIMANTAN TENGAH",
      "slug": "kalimantan-tengah",
      "lists": [{
        "name": "Pemerintah Provinsi Kalimantan Tengah",
        "url": "https://corona.kalteng.go.id/"
      }]
    }
  }, {
    "attributes": {
      "group_name": "KALIMANTAN TIMUR",
      "slug": "kalimantan-timur",
      "lists": [{
        "name": "Pemerintah Provinsi Kalimantan Timur",
        "url": "https://covid19.kaltimprov.go.id/"
      }]
    }
  }, {
    "attributes": {
      "group_name": "KALIMANTAN UTARA",
      "slug": "kalimantan-utara",
      "lists": [{
        "name": "Pemerintah Provinsi Kalimantan Utara",
        "url": "https://humas.kaltaraprov.go.id/"
      }]
    }
  }, {
    "attributes": {
      "group_name": "KEPULAUAN BANGKA BELITUNG",
      "slug": "kepulauan-bangka-belitung",
      "lists": [{
        "name": "Pemerintah Provinsi Kepulauan Bangka Belitung",
        "url": "https://covid19.babelprov.go.id/"
      }]
    }
  }, {
    "attributes": {
      "group_name": "KEPULAUAN RIAU",
      "slug": "kepulauan-riau",
      "lists": [{
        "name": "Pemerintah Provinsi Kepulauan Riau",
        "url": "https://corona.kepriprov.go.id/"
      }, {
        "name": "Pemerintah Kabupaten Bintan",
        "url": "https://gugustugas.bintankab.go.id/"
      }, {
        "name": "Pemerintah Kabupaten Kepulauan Anambas",
        "url": "https://bpbd.anambaskab.go.id/"
      }, {
        "name": "Pemerintah Kabupaten Natuna",
        "url": "https://covid19.natunakab.go.id/"
      }, {
        "name": "Pemerintah Kota Batam",
        "url": "https://lawancorona.batam.go.id"
      }]
    }
  }, {
    "attributes": {
      "group_name": "LAMPUNG",
      "slug": "lampung",
      "lists": [{
        "name": "Pemerintah Provinsi Lampung",
        "url": "http://geoportal.lampungprov.go.id/corona/"
      }]
    }
  }, {
    "attributes": {
      "group_name": "MALUKU",
      "slug": "maluku",
      "lists": [{
        "name": "Pemerintah Provinsi Maluku",
        "url": "https://corona.malukuprov.go.id/"
      }]
    }
  }, {
    "attributes": {
      "group_name": "MALUKU UTARA",
      "slug": "maluku-utara",
      "lists": [{
        "name": "Pemerintah Provinsi Maluku Utara",
        "url": "http://corona.malutprov.go.id/"
      }]
    }
  }, {
    "attributes": {
      "group_name": "NUSA TENGGARA BARAT",
      "slug": "nusa-tenggara-barat",
      "lists": [{
        "name": "Pemerintah Provinsi Nusa Tenggara Barat",
        "url": "https://corona.ntbprov.go.id/"
      }]
    }
  }, {
    "attributes": {
      "group_name": "PAPUA",
      "slug": "papua",
      "lists": [{
        "name": "Pemerintah Provinsi Papua",
        "url": "https://corona.papua.go.id/"
      }]
    }
  }, {
    "attributes": {
      "group_name": "RIAU",
      "slug": "riau",
      "lists": [{
        "name": "Pemerintah Provinsi Riau",
        "url": "https://corona.riau.go.id/"
      }]
    }
  }, {
    "attributes": {
      "group_name": "SULAWESI BARAT",
      "slug": "sulawesi-barat",
      "lists": [{
        "name": "Pemerintah Provinsi Sulawesi Barat",
        "url": "https://covid19.sulbarprov.go.id/"
      }]
    }
  }, {
    "attributes": {
      "group_name": "SULAWESI SELATAN",
      "slug": "sulawesi-selatan",
      "lists": [{
        "name": "Pemerintah Provinsi Sulawesi Selatan",
        "url": "https://covid19.sulselprov.go.id/"
      }]
    }
  }, {
    "attributes": {
      "group_name": "SULAWESI TENGGARA",
      "slug": "sulawesi-tenggara",
      "lists": [{
        "name": "Pemerintah Provinsi Sulawesi Tenggara",
        "url": "http://corona.sultraprov.go.id/"
      }]
    }
  }, {
    "attributes": {
      "group_name": "SULAWESI UTARA",
      "slug": "sulawesi-utara",
      "lists": [{
        "name": "Pemerintah Provinsi Sulawesi Utara",
        "url": "https://corona.sulutprov.go.id/"
      }, {
        "name": "Pemerintah Kabupaten Bolaang Mongondow",
        "url": "https://covid19.bolmongkab.go.id/"
      }]
    }
  }, {
    "attributes": {
      "group_name": "SUMATERA BARAT",
      "slug": "sumatera-barat",
      "lists": [{
        "name": "Pemerintah Provinsi Sumatera Barat",
        "url": "https://corona.sumbarprov.go.id/"
      }, {
        "name": "Pemerintah Kabupaten Agam",
        "url": "http://covid19.agamkab.go.id/"
      }, {
        "name": "Pemerintah Kabupaten Lima Puluh Kota",
        "url": "https://covid19.limapuluhkotakab.go.id/"
      }, {
        "name": "Pemerintah Kabupaten Padang Pariaman",
        "url": "https://covid19.padangpariamankab.go.id/"
      }, {
        "name": "Pemerintah Kabupaten Pasaman",
        "url": "http://corona.pasamankab.go.id/"
      }, {
        "name": "Pemerintah Kabupaten Pasaman Barat",
        "url": "https://corona.pasamanbaratkab.go.id/"
      }, {
        "name": "Pemerintah Kabupaten Pesisir Selatan",
        "url": "https://covid19.pesisirselatankab.go.id/"
      }, {
        "name": "Pemerintah Kota Padang",
        "url": "http://corona.padang.go.id/"
      }, {
        "name": "Pemerintah Kota Padang Panjang",
        "url": "https://corona.padangpanjang.go.id/"
      }, {
        "name": "Pemerintah Kota Payakumbuh",
        "url": "https://covid19.payakumbuhkota.go.id/"
      }, {
        "name": "Pemerintah Kota Solok",
        "url": "https://corona.solokkota.go.id/"
      }]
    }
  }, {
    "attributes": {
      "group_name": "SUMATERA SELATAN",
      "slug": "sumatera-selatan",
      "lists": [{
        "name": "Pemerintah Provinsi Sumatera Selatan",
        "url": "http://corona.sumselprov.go.id/index.php?module=home&id=1"
      }, {
        "name": "Pemerintah Kabupaten Musi Banyuasin",
        "url": "https://covid19.mubakab.go.id/"
      }, {
        "name": "Pemerintah Kota Palembang",
        "url": "https://hallo.palembang.go.id/Corona"
      }]
    }
  }, {
    "attributes": {
      "group_name": "SUMATERA UTARA",
      "slug": "sumatera-utara",
      "lists": [{
        "name": "Pemerintah Provinsi Sumatera Utara",
        "url": "http://covid19.sumutprov.go.id/"
      }, {
        "name": "Pemerintah Kabupaten Deli Serdang",
        "url": "http://covid19.deliserdangkab.go.id/"
      }, {
        "name": "Pemerintah Kabupaten Langkat",
        "url": "https://coronainfo.langkatkab.go.id/"
      }, {
        "name": "Pemerintah Kota Tebing Tinggi",
        "url": "https://covid19.tebingtinggikota.go.id/"
      }]
    }
  }, {
    "attributes": {
      "group_name": "YOGYAKARTA",
      "slug": "yogyakarta",
      "lists": [{
        "name": "Pemerintah Provinsi DI Yogyakarta",
        "url": "https://corona.jogjaprov.go.id/"
      }, {
        "name": "Pemerintah Kota Yogyakarta",
        "url": "https://corona.jogjakota.go.id/"
      }, {
        "name": "Pemerintah Kabupaten Bantul",
        "url": "https://corona.bantulkab.go.id/"
      }, {
        "name": "Pemerintah Kabupaten Gunungkidul",
        "url": "https://corona.gunungkidulkab.go.id/"
      }, {
        "name": "Pemerintah Kabupaten Kulon Progo",
        "url": "https://kulonprogokab.go.id/corona/"
      }, {
        "name": "Pemerintah Kabupaten Sleman",
        "url": "https://corona.slemankab.go.id/"
      }]
    }
  }, {
    "attributes": {
      "group_name": "Lainnya",
      "slug": "lainnya",
      "lists": [{
        "name": "KawalCOVID19",
        "url": "https://kawalcovid19.id/"
      }]
    }
  }]
}
